prognosis/__init__.py
prognosis/country.py
prognosis/country_group.py
prognosis/helper.py
prognosis/widget.py
prognosis/com/__init__.py
prognosis/com/country.py
prognosis/com/topics.py
prognosis-0.0.91.dist-info/METADATA
prognosis-0.0.91.dist-info/WHEEL
prognosis-0.0.91.dist-info/top_level.txt
prognosis-0.0.91.dist-info/RECORD
